nginx.py
python_nginx-1.5.7.dist-info/LICENSE
python_nginx-1.5.7.dist-info/METADATA
python_nginx-1.5.7.dist-info/WHEEL
python_nginx-1.5.7.dist-info/top_level.txt
python_nginx-1.5.7.dist-info/RECORD
